aws_browser/__init__.py
aws_browser/aws.py
aws_browser/browser.py
aws_browser/cli.py
aws_browser/constants.py
aws_browser-0.1.4.dist-info/LICENSE
aws_browser-0.1.4.dist-info/METADATA
aws_browser-0.1.4.dist-info/WHEEL
aws_browser-0.1.4.dist-info/entry_points.txt
aws_browser-0.1.4.dist-info/RECORD
