Metadata-Version: 2.1
Name: aws-browser
Version: 0.1.4
Summary: 
Author: Ben Bridts
Requires-Python: >=3.9,<4.0
Classifier: Programming Language :: Python :: 3
Classifier: Programming Language :: Python :: 3.9
Classifier: Programming Language :: Python :: 3.10
Classifier: Programming Language :: Python :: 3.11
Requires-Dist: boto3 (>=1.21.1,<2.0.0)
Requires-Dist: requests (>=2.27.1,<3.0.0)
